simple_perceptron/__init__.py
simple_perceptron/perceptron.py
SimplePerceptron_package_Ankit_Mehra-0.0.4.dist-info/LICENSE
SimplePerceptron_package_Ankit_Mehra-0.0.4.dist-info/METADATA
SimplePerceptron_package_Ankit_Mehra-0.0.4.dist-info/WHEEL
SimplePerceptron_package_Ankit_Mehra-0.0.4.dist-info/top_level.txt
SimplePerceptron_package_Ankit_Mehra-0.0.4.dist-info/RECORD
