Metadata-Version: 2.1
Name: SimplePerceptron_package-Ankit-Mehra
Version: 0.0.4
Summary: A small example package for perceptron
Home-page: https://github.com/Ankit-Mehra/SimplePerceptron-package
Author: Ankit-Mehra
Author-email: ankitmehra1986@gmail.com
License: UNKNOWN
Project-URL: Bug Tracker, https://github.com/Ankit-Mehra/SimplePerceptron-package/issues
Platform: UNKNOWN
Classifier: Programming Language :: Python :: 3
Classifier: License :: OSI Approved :: MIT License
Classifier: Operating System :: OS Independent
Requires-Python: >=3.6
License-File: LICENSE
